process_redis_events/__init__.py
process_redis_events/chunk.py
process_redis_events/constants.py
process_redis_events/create_group.py
process_redis_events/get_entries.py
process_redis_events/heartbeat_manager.py
process_redis_events/parse_json.py
process_redis_events/py.typed
process_redis_events/queue_item.py
process_redis_events/result_of.py
process_redis_events/stream.py
process_redis_events/stream_event.py
process_redis_events/telemetry.py
process_redis_events/types.py
process_redis_events-5.0.6.dist-info/METADATA
process_redis_events-5.0.6.dist-info/WHEEL
process_redis_events-5.0.6.dist-info/licenses/LICENSE
process_redis_events-5.0.6.dist-info/RECORD
