Metadata-Version: 2.4
Name: process-redis-events
Version: 5.0.6
Summary: A Python library for processing Redis Stream events with consumer groups
Author-email: Michael Leaney <leahcimic@gmail.com>
License: ISC
License-File: LICENSE
Requires-Python: >=3.11
Requires-Dist: opentelemetry-api>=1.20.0
Requires-Dist: pydantic>=2.0.0
Requires-Dist: redis>=5.0.0
Requires-Dist: typing-extensions>=4.5.0
Provides-Extra: dev
Requires-Dist: black>=23.7.0; extra == 'dev'
Requires-Dist: mypy>=1.5.0; extra == 'dev'
Requires-Dist: pytest-asyncio>=0.21.0; extra == 'dev'
Requires-Dist: pytest-timeout>=2.1.0; extra == 'dev'
Requires-Dist: pytest>=7.4.0; extra == 'dev'
Requires-Dist: ruff>=0.0.286; extra == 'dev'
